README.md
setup.py
bin/pyronos
pyronos/__init__.py
pyronos/pyronos.py
pyronos/user_agents.py
pyronos.egg-info/PKG-INFO
pyronos.egg-info/SOURCES.txt
pyronos.egg-info/dependency_links.txt
pyronos.egg-info/requires.txt
pyronos.egg-info/top_level.txt