Metadata-Version: 2.1
Name: pyronos
Version: 0.0.1
Summary: Simple and sweet load testing module.
Home-page: https://github.com/0x01h/pyronos
Author: Orçun Özdemir
Author-email: benorcunozdemir@gmail.com
License: WTFPL
Platform: UNKNOWN
Classifier: Development Status :: 5 - Production/Stable
Classifier: Environment :: Console
Classifier: Intended Audience :: End Users/Desktop
Classifier: Natural Language :: English
Classifier: Topic :: Software Development :: Testing
Classifier: Programming Language :: Python :: 3
Classifier: Operating System :: OS Independent
